scorecovid.py
scorecovid-0.0.10.dist-info/METADATA
scorecovid-0.0.10.dist-info/WHEEL
scorecovid-0.0.10.dist-info/entry_points.txt
scorecovid-0.0.10.dist-info/top_level.txt
scorecovid-0.0.10.dist-info/RECORD
