Metadata-Version: 2.1
Name: scorecovid
Version: 0.0.10
Summary: A package for scoring covid-19 country policies
Home-page: https://github.com/y-takefuji/score-covid-19-policy
Author: yoshiyasu takefuji
Author-email: takefuji@keio.jp
License: UNKNOWN
Project-URL: Bug Tracker, https://github.com/y-takefuji/score-covid-19-policy
Platform: UNKNOWN
Classifier: Programming Language :: Python :: 3
Classifier: License :: OSI Approved :: MIT License
Classifier: Operating System :: OS Independent
Requires-Python: >=3.8
